.bumpversion.cfg
.readthedocs.yaml
CONTRIBUTING.md
LICENSE
MANIFEST.in
Makefile
README.md
pyproject.toml
setup.py
age3d/__init__.py
age3d/__main__.py
age3d/_version.py
age3d/age3d.py
age3d/examples.ipynb
age3d.egg-info/PKG-INFO
age3d.egg-info/SOURCES.txt
age3d.egg-info/dependency_links.txt
age3d.egg-info/requires.txt
age3d.egg-info/top_level.txt
age3d/models/monkey.stl
age3d/models/monkey_cleaned.stl
age3d/tests/monkey_triangles.npy
age3d/tests/monkey_vertices.npy
age3d/tests/test_all.py
docs/Makefile
docs/conf.py
docs/documentation.rst
docs/examples.rst
docs/getting_started.rst
docs/index.rst
docs/make.bat
docs/img/monkey.png
docs/img/monkey_accessible.png
docs/img/monkey_below_above_between.png
docs/img/monkey_bound_height.png
docs/img/monkey_erode.png
docs/img/monkey_erode_direction.png
docs/img/monkey_erode_wireframe.png
docs/img/monkey_erode_wireframe_direction.png
docs/img/monkey_min_max.png
docs/img/monkey_neighbors.png
docs/img/monkey_pc.png
docs/img/monkey_subdivision.png
docs/img/monkey_wireframe.png