Metadata-Version: 2.1
Name: age3d
Version: 0.4.0
Summary: Aging 3D models
Author-email: Abhishek Chaudhary <ac5003@columbia.edu>
License:                                  Apache License
Project-URL: repository, https://github.com/A-Chaudhary/age3d
Classifier: Development Status :: 2 - Pre-Alpha
Classifier: Programming Language :: Python :: Implementation :: CPython
Classifier: Programming Language :: Python :: Implementation :: PyPy
Classifier: Programming Language :: Python :: 3
Classifier: Programming Language :: Python :: 3.7
Classifier: Programming Language :: Python :: 3.8
Classifier: Programming Language :: Python :: 3.9
Classifier: Programming Language :: Python :: 3.10
Classifier: Programming Language :: Python :: 3.11
Requires-Python: >=3.7
Provides-Extra: develop
License-File: LICENSE
